oyehr_tool_package/__init__.py
oyehr_tool_package/tools/__init__.py
oyehr_tool_package/tools/my_tool_1.py
oyehr_tool_package/tools/my_tool_2.py
oyehr_tool_package/tools/utils.py
oyehr_tool_package/yamls/my_tool_1.yaml
oyehr_tool_package/yamls/my_tool_2.yaml
oyehr_tools_package-0.0.4.dist-info/METADATA
oyehr_tools_package-0.0.4.dist-info/WHEEL
oyehr_tools_package-0.0.4.dist-info/entry_points.txt
oyehr_tools_package-0.0.4.dist-info/top_level.txt
oyehr_tools_package-0.0.4.dist-info/RECORD
