Metadata-Version: 2.1
Name: oyehr-tools-package
Version: 0.0.4
Summary: This is my tools package
